papaya/__init__.py
papaya/analyze_failure.py
papaya/cli.py
papaya/code_repair.py
papaya/discord_utils.py
papaya/github_utils.py
papaya/main.py
papaya/monitor.py
papaya/postgres_utils.py
papaya_debugger-0.1.1.dist-info/METADATA
papaya_debugger-0.1.1.dist-info/WHEEL
papaya_debugger-0.1.1.dist-info/entry_points.txt
papaya_debugger-0.1.1.dist-info/top_level.txt
papaya_debugger-0.1.1.dist-info/RECORD
