Metadata-Version: 2.4
Name: papaya-debugger
Version: 0.1.1
Summary: Intelligent debugging tool for Apache Spark jobs
Author-email: Lychee Development <abhi@trylychee.dev>
License: MIT
Project-URL: Homepage, https://github.com/lychee-development/papaya
Project-URL: Bug Tracker, https://github.com/lychee-development/papaya/issues
Classifier: Programming Language :: Python :: 3
Classifier: License :: OSI Approved :: MIT License
Classifier: Operating System :: OS Independent
Classifier: Topic :: Software Development :: Debuggers
Classifier: Topic :: Software Development :: Libraries :: Python Modules
Requires-Python: >=3.10
Requires-Dist: discord.py>=2.3.2
Requires-Dist: google-genai>=1.14.0
Requires-Dist: pygithub>=2.6.1
Requires-Dist: python-dotenv>=1.0.0
Requires-Dist: requests>=2.32.0
Dynamic: requires-python
